MANIFEST.in
README
TODO
setup.py
bin/pylisp-ng
pyLisp_NG.egg-info/PKG-INFO
pyLisp_NG.egg-info/SOURCES.txt
pyLisp_NG.egg-info/dependency_links.txt
pyLisp_NG.egg-info/top_level.txt
pylispng/__init__.py
pylispng/lisp.py
pylispng/meta.py
pylispng/test/__init__.py
pylispng/test/test_lisp.py
pylispng/util/__init__.py
pylispng/util/dist.py
pylispng/util/sprint.py
pylispng/util/test/__init__.py
pylispng/util/test/test_sprint.py
pylispng/util/test/test_util.py