Metadata-Version: 1.0
Name: pyLisp-NG
Version: 2.0.0
Summary: A very simple implementation of Lisp in Python that is perfectly suitable for Python projects needing Lisp-like capabilities.
Home-page: https://launchpad.net/pylist-ng
Author: William S. Annis, Duncan McGreggor
Author-email: duncan@adytum.us
License: LGPL 2.1
Platform: UNKNOWN
Classifier: Development Status :: 4 - Beta
Classifier: Intended Audience :: Developers
Classifier: Intended Audience :: Science/Research
Classifier: Programming Language :: Python
Classifier: Programming Language :: Lisp
Classifier: Topic :: Software Development :: Interpreters
Classifier: License :: OSI Approved :: GNU Library or Lesser General Public License (LGPL)
